doc/Documentation.mm
doc/Makefile
doc/Tutorial.mm
doc/conf.py
doc/index.rst
doc/overview.png
doc/overview.puml
doc/overview.rst
doc/overview.svg
doc/whatchanged.rst
doc/browsertools/__init__.py
doc/browsertools/index.rst
doc/browsertools/introduction.rst
doc/component/config.rst
doc/component/context.rst
doc/component/dbutils.rst
doc/component/exceptions.rst
doc/component/i18n.rst
doc/component/index.rst
doc/component/introduction.rst
doc/component/migration.rst
doc/component/modelinterface.rst
doc/component/mysqlsupport.rst
doc/component/postgresqlsupport.rst
doc/component/pyproject.toml.rst
doc/component/setup.cfg.rst
doc/component/sqlalchemysupport.rst
doc/component/sqlitesupport.rst
doc/devmanual/conventions.rst
doc/devmanual/dependencyinjection.rst
doc/devmanual/depinjection.png
doc/devmanual/depinjection.svg
doc/devmanual/devenv.rst
doc/devmanual/index.rst
doc/devmanual/ownwidget.rst
doc/devmanual/sourcecode.rst
doc/devmanual/testing.rst
doc/devtools/index.rst
doc/devtools/introduction.rst
doc/devtools/stubble.rst
doc/devtools/tofu.rst
doc/devtools/tools.rst
doc/devtools/xmlref.rst
doc/discuss/on_refresh.rst
doc/domain/index.rst
doc/domain/mail.rst
doc/domain/rst.rst
doc/domain/systemaccountmodel.rst
doc/domain/systemaccountui.rst
doc/domain/workflowmodel.rst
doc/domain/workflowui.rst
doc/howto/csrf.rst
doc/howto/customisingcss.rst
doc/howto/customisingerrorpages.rst
doc/howto/docker.rst
doc/howto/dynamiccontenterrors.rst
doc/howto/eventresult.rst
doc/howto/index.rst
doc/howto/multihomed.rst
doc/howto/nginx.rst
doc/howto/optimisticlocking.rst
doc/howto/pager.png
doc/howto/pager.svg
doc/howto/paginglonglists.rst
doc/howto/paypal.puml
doc/howto/paypal.rst
doc/howto/plotly.rst
doc/howto/plotly2.rst
doc/howto/programmaticparameterised.rst
doc/howto/refreshingwidgets.rst
doc/howto/responsivedisclosure.rst
doc/howto/transitionstoparameterised.rst
doc/stubble/index.rst
doc/stubble/introduction.rst
doc/tofu/index.rst
doc/tofu/introduction.rst
reahl_doc-7.0.3.dist-info/LICENSE
reahl_doc-7.0.3.dist-info/METADATA
reahl_doc-7.0.3.dist-info/WHEEL
reahl_doc-7.0.3.dist-info/entry_points.txt
reahl_doc-7.0.3.dist-info/reahl-component.toml
reahl_doc-7.0.3.dist-info/top_level.txt
reahl_doc-7.0.3.dist-info/RECORD
