Metadata-Version: 2.1
Name: reahl-doc
Version: 7.0.3
Summary: Documentation and examples for Reahl.
Author-email: Iwan Vosloo <iwan@reahl.org>, Craig Sparks <craig@reahl.org>
Classifier: Development Status :: 5 - Production/Stable
Classifier: Intended Audience :: Developers
Classifier: License :: OSI Approved
Classifier: Operating System :: OS Independent
Classifier: Programming Language :: Python :: 3
Classifier: Topic :: Software Development :: Documentation
Requires-Python: >=3.8
License-File: LICENSE
Requires-Dist: reahl-web <7.1,>=7.0
Requires-Dist: reahl-component <7.1,>=7.0
Requires-Dist: reahl-sqlalchemysupport <7.1,>=7.0
Requires-Dist: reahl-web-declarative <7.1,>=7.0
Requires-Dist: reahl-domain <7.1,>=7.0
Requires-Dist: reahl-domainui <7.1,>=7.0
Requires-Dist: reahl-commands <7.1,>=7.0
Requires-Dist: reahl-dev <7.1,>=7.0
Requires-Dist: reahl-paypalsupport <7.1,>=7.0
Requires-Dist: pytest >=3.0
Requires-Dist: setuptools >=51.0.0
Requires-Dist: plotly <5.18.99999,>=5.1.0
Requires-Dist: SQLAlchemy <2.1.999,>=1.4
Provides-Extra: test
Requires-Dist: pytest >=3.0 ; extra == 'test'
Requires-Dist: Sphinx ; extra == 'test'
Requires-Dist: sphinxcontrib-plantuml ; extra == 'test'
Requires-Dist: sphinxcontrib-applehelp ==1.0.4 ; extra == 'test'
Requires-Dist: sphinxcontrib-devhelp ==1.0.2 ; extra == 'test'
Requires-Dist: sphinxcontrib-htmlhelp ==2.0.1 ; extra == 'test'
Requires-Dist: sphinxcontrib-jsmath ==1.0.1 ; extra == 'test'
Requires-Dist: sphinxcontrib-qthelp ==1.0.3 ; extra == 'test'
Requires-Dist: sphinxcontrib-serializinghtml ==1.1.5 ; extra == 'test'
Requires-Dist: flaky >=3.7.0 ; extra == 'test'
Requires-Dist: reahl-tofu ; extra == 'test'
Requires-Dist: reahl-stubble ; extra == 'test'
Requires-Dist: reahl-dev ; extra == 'test'
Requires-Dist: reahl-webdev ; extra == 'test'
Requires-Dist: reahl-browsertools ; extra == 'test'
Requires-Dist: reahl-postgresqlsupport ; extra == 'test'
Requires-Dist: reahl-sqlitesupport ; extra == 'test'
Requires-Dist: reahl-mysqlsupport ; extra == 'test'
